pyroc.py
pyroc-0.1.1.dist-info/LICENSE
pyroc-0.1.1.dist-info/METADATA
pyroc-0.1.1.dist-info/WHEEL
pyroc-0.1.1.dist-info/top_level.txt
pyroc-0.1.1.dist-info/RECORD
