Metadata-Version: 2.1
Name: pyroc
Version: 0.1.1
Summary: Python tools for working with the AUROC
Home-page: https://github.com/alistairewj/pyroc
Author: Alistair Johnson, Lucas Bulgarelli
Author-email: aewj@mit.edu
License: MIT
Keywords: AUROC AUC DeLong p-value
Platform: UNKNOWN
Requires-Dist: pandas (>=0.22.0)
Requires-Dist: numpy (>=1.12.1)
Requires-Dist: scipy (>=0.18.1)
